c3/__init__.py
c3/consts.py
c3/controldevice.py
c3/core.py
c3/crc.py
c3/rtlog.py
c3/utils.py
zkaccess_c3-0.0.15.dist-info/licenses/LICENSE
zkaccess_c3-0.0.15.dist-info/METADATA
zkaccess_c3-0.0.15.dist-info/WHEEL
zkaccess_c3-0.0.15.dist-info/top_level.txt
zkaccess_c3-0.0.15.dist-info/RECORD
