Metadata-Version: 2.4
Name: zkaccess_c3
Version: 0.0.15
Summary: A native Python library for communicating with the ZKAccess C3 and inBio Door Access Control Panels.
Author-email: Vwout <vwout@users.noreply.github.com>
Project-URL: Homepage, https://github.com/vwout/zkaccess-c3-py
Project-URL: Bug Tracker, https://github.com/vwout/zkaccess-c3-py/issues
Classifier: Programming Language :: Python :: 3
Classifier: Operating System :: OS Independent
Requires-Python: >=3.7
License-File: LICENSE
Dynamic: license-file
